Metadata-Version: 2.1
Name: spidev2
Version: 0.9.0
Summary: Pure-python interface to Linux spidev.
Home-page: http://github.com/vpelletier/python-spidev2
Author: Vincent Pelletier
Author-email: plr.vincent@gmail.com
License: GPLv3+
Keywords: linux SPI spidev
Platform: linux
Classifier: Intended Audience :: Developers
Classifier: License :: OSI Approved :: GNU General Public License v3 or later (GPLv3+)
Classifier: Operating System :: POSIX :: Linux
Classifier: Programming Language :: Python :: 3
Classifier: Programming Language :: Python :: Implementation :: CPython
Classifier: Programming Language :: Python :: Implementation :: PyPy
Classifier: Topic :: Software Development :: Libraries
Classifier: Topic :: System :: Hardware :: Hardware Drivers
License-File: COPYING
